examples/1_solve_simple.py
examples/2_solve_multivariate.py
examples/3_solve_stochastic.py
examples/__init__.py
solver/Duelist_Algorithm.py
solver/__init__.py
DuelistAlgorithmPython-1.0.dist-info/LICENSE
DuelistAlgorithmPython-1.0.dist-info/METADATA
DuelistAlgorithmPython-1.0.dist-info/WHEEL
DuelistAlgorithmPython-1.0.dist-info/top_level.txt
DuelistAlgorithmPython-1.0.dist-info/RECORD
