Metadata-Version: 2.1
Name: DuelistAlgorithmPython
Version: 1.0
Summary: Implementation of Duelist Algorithm in Python
Home-page: UNKNOWN
Author: Sin Yong Teng
Author-email: tsyet12@gmail.com
License: UNKNOWN
Platform: UNKNOWN
